smcs/__init__.py
smcs/_typing.py
smcs/agents/__init__.py
smcs/agents/arima_agent.py
smcs/agents/base.py
smcs/agents/dlm_agent.py
smcs/agents/garch_agent.py
smcs/agents/sv_agent.py
smcs/algorithms/__init__.py
smcs/algorithms/auxiliary.py
smcs/algorithms/bootstrap.py
smcs/algorithms/liu_west.py
smcs/algorithms/pmcmc.py
smcs/algorithms/smc2.py
smcs/algorithms/storvik.py
smcs/algorithms/waste_free.py
smcs/config/__init__.py
smcs/config/settings.py
smcs/core/__init__.py
smcs/core/particles.py
smcs/core/resampling.py
smcs/core/weights.py
smcs/io/__init__.py
smcs/io/dataframe.py
smcs/models/__init__.py
smcs/models/arima.py
smcs/models/base.py
smcs/models/distributions.py
smcs/models/dlm.py
smcs/models/factor.py
smcs/models/garch.py
smcs/models/regime.py
smcs/models/sv.py
smcs-0.1.0.dist-info/METADATA
smcs-0.1.0.dist-info/WHEEL
smcs-0.1.0.dist-info/licenses/LICENSE
smcs-0.1.0.dist-info/RECORD
