Metadata-Version: 2.4
Name: smcs
Version: 0.1.0
Summary: JAX-based Sequential Monte Carlo library for time series prediction
Project-URL: Homepage, https://github.com/HarudoBoruzu/smcs
Project-URL: Repository, https://github.com/HarudoBoruzu/smcs.git
Project-URL: Issues, https://github.com/HarudoBoruzu/smcs/issues
Project-URL: Documentation, https://github.com/HarudoBoruzu/smcs#readme
Author: HarudoBoruzu
License-Expression: Apache-2.0
License-File: LICENSE
Keywords: bayesian-inference,jax,particle-filter,sequential-monte-carlo,state-space-models,time-series
Classifier: Development Status :: 3 - Alpha
Classifier: Intended Audience :: Science/Research
Classifier: License :: OSI Approved :: Apache Software License
Classifier: Operating System :: OS Independent
Classifier: Programming Language :: Python :: 3
Classifier: Programming Language :: Python :: 3.10
Classifier: Programming Language :: Python :: 3.11
Classifier: Programming Language :: Python :: 3.12
Classifier: Topic :: Scientific/Engineering
Classifier: Topic :: Scientific/Engineering :: Mathematics
Classifier: Typing :: Typed
Requires-Python: >=3.10
Requires-Dist: beartype>=0.16.0
Requires-Dist: chex>=0.1.85
Requires-Dist: jax>=0.4.20
Requires-Dist: jaxlib>=0.4.20
Requires-Dist: jaxtyping>=0.2.25
Requires-Dist: loguru>=0.7.2
Requires-Dist: numpy>=1.24.0
Requires-Dist: pandas>=2.0.0
Requires-Dist: pydantic>=2.5.0
Provides-Extra: dev
Requires-Dist: hypothesis>=6.90.0; extra == 'dev'
Requires-Dist: mypy>=1.7.0; extra == 'dev'
Requires-Dist: pytest-benchmark>=4.0.0; extra == 'dev'
Requires-Dist: pytest-cov>=4.1.0; extra == 'dev'
Requires-Dist: pytest>=7.4.0; extra == 'dev'
Requires-Dist: ruff>=0.1.0; extra == 'dev'
Provides-Extra: docs
Requires-Dist: mkdocs-material>=9.5.0; extra == 'docs'
Requires-Dist: mkdocs>=1.5.0; extra == 'docs'
Requires-Dist: mkdocstrings[python]>=0.24.0; extra == 'docs'
